{
  "slug": "cryptool-partners-with-bscs-to-run-launchpad-pools-end-to-en",
  "title": "Cryptool partners with BSCS to run launchpad pools end to end",
  "date": "2025-02-26T12:40:00.000Z",
  "content_html": "<p>Cryptool is collaborating with several established launchpads to host and manage their pool events directly on the platform. The first named partner is BSCS, a long-running launchpad in the BNB ecosystem.</p>\n<p>For the launchpads, Cryptool takes over the operational work that used to live in spreadsheets: vesting management, refunds, distributions and member communication. For investors, every pool they participate in across these launchpads now appears in one dashboard, with consistent reporting and a single distribution flow.</p>\n<p>More launchpad partnerships are in the pipeline and will be announced as they go live.</p>",
  "type": "news",
  "author": "Cryptool",
  "excerpt_html": "Cryptool is collaborating with several established launchpads to host and manage their pool events directly on the platform. The first named partner is BSCS, a",
  "tags": [
    "Partnership"
  ]
}