{
  "slug": "portfolio-and-otc-market-are-live-with-early-stage-investmen",
  "title": "Portfolio and OTC Market are live with early-stage investments",
  "date": "2026-02-23T11:34:00.000Z",
  "content_html": "<p>Cryptool has officially launched the Portfolio and OTC Market modules, now including early-stage crypto investments.</p>\n<p><strong>Portfolio</strong></p>\n<ul><li>Track crypto holdings from one place</li><li>View status, vesting schedules and next unlock dates</li><li>Monitor performance and historical trends</li><li>Manage early-stage investments alongside the rest of your portfolio</li></ul>\n<p><strong>OTC Market</strong></p>\n<ul><li>Trade both vested and unvested tokens directly</li><li>Execute large-volume trades safely and efficiently</li><li>Access exclusive early-stage investment opportunities</li><li>Transparent pricing and fast settlement</li></ul>\n<p>This release brings together the full Cryptool stack: fundraising, portfolio management and OTC, all on one platform.</p>",
  "type": "news",
  "author": "Cryptool",
  "excerpt_html": "Cryptool has officially launched the Portfolio and OTC Market modules, now including early-stage crypto investments. **Portfolio** - Track crypto holdings fro",
  "tags": [
    "Feature"
  ]
}