{
  "slug": "how-cryptool-s-non-custodial-model-changes-fund-administrati",
  "title": "How Cryptool's Non-Custodial Model Changes Fund Administration for Community VCs",
  "date": "2026-07-16T09:03:20.062Z",
  "content_html": "<p>Community VCs and crypto syndicates share a common problem. They want to pool capital, track member allocations, and run distributions without handing their assets to a third party. Most traditional fund administration setups assume custody, which adds risk, cost, and a layer of trust the group never asked for. Non-custodial fund administration takes the opposite approach: the assets stay in the group's own wallets, and the platform handles the record-keeping and coordination around them.</p>\n<p>Here is how that works in practice on Cryptool.</p>\n<h2><strong>What non-custodial actually means</strong></h2>\n<p>On Cryptool, wallet connections are read-only by default. The platform never holds private keys, never holds funds, and never has signing authority. Every transaction is signed by the user's own wallet directly, and Cryptool does not take ownership or control of any investment, per its published portfolio and raise terms.</p>\n<p>For a community VC, that removes the biggest objection to using a fund administration tool at all. There is no platform account holding pooled capital, so there is no custody dispute to have and no third party to trust with the treasury. The group keeps its keys. Cryptool keeps the books.</p>\n<h2><strong>Running a group without giving up control</strong></h2>\n<p>Cryptool's Groups module is built for exactly this workflow. A syndicate lead can create and manage a group, add members, and organize them into up to 5 custom member tiers. Pools can be created and managed inside the group, and ROI and P&amp;L are tracked per group, so the lead can see how each vehicle is performing without exporting anything to a spreadsheet.</p>\n<p>The Portfolio module sits alongside it, giving a bird's-eye view of individual or group investments, including tokens, unvested allocations, and custom assets, with P&amp;L and ROI indicators. Because coverage spans all chains and all wallets for over 90% of the platform's features, a syndicate holding positions across many networks sees them in one place.</p>\n<h2><strong>Raises and distributions, still non-custodial</strong></h2>\n<p>The part of fund administration that usually forces custody is the raise itself. Cryptool's Raise module handles it differently. A group can run multi-stage rounds with configurable caps, vesting schedules, and claim windows, with whitelist and KYC built in. Once the raise completes, distribution happens automatically on-chain, with a distribution fee charged per batch. Groups using the Raise module set a group fee of at least 2%.</p>\n<p>Vesting is defined by the admin at deal creation: cliff, duration, and unlock cadence. From there the platform does the follow-up work. Allocations are updated at least hourly, tokens are transferred to participants' wallets at each vesting unlock event, and the platform sends reminders when unlocks are due. That replaces the spreadsheet-and-calendar routine most syndicate operators know too well. For a closer look at that workflow, see [how crypto syndicates automate member allocations and distributions](/blog/how-crypto-syndicates-automate-member-allocations-and-distri).</p>\n<p>On-chain modules are live today on Ethereum, BNB Chain, and MultiversX, with more networks on the way, including Polygon, Arbitrum, Avalanche, Optimism, and Solana.</p>\n<h2><strong>What it costs</strong></h2>\n<p>Cryptool's pricing is public. The Free tier is $0 and covers 1 wallet on 1 chain, enough to evaluate the platform. Individual plans start at $2.99 per month for Users and $7.99 per month for Advanced Users. The Manager plan, built for VCs and funds, starts at $39.99 per month, and Enterprise starts at $119.99 per month with white label options, a custom group URL, and API integration. For a broader picture of how the modules fit together, read [crypto fund management in one place](/blog/crypto-fund-management-in-one-place-dealflow-raises-distribu).</p>\n<h2><strong>Common questions</strong></h2>\n<h3>What is non-custodial fund administration?</h3>\n<p></p>\n<p>It means the platform administers the fund's records, allocations, and distributions without ever holding the fund's assets. On Cryptool, wallet connections are read-only by default and every transaction is signed by the user's own wallet.</p>\n<h3>How does Cryptool keep assets secure in a non-custodial model?</h3>\n<p></p>\n<p>Cryptool never holds private keys, funds, or signing authority, and it does not take ownership or control of investments. Assets remain in the wallets the group already controls.</p>\n<h3>Can Cryptool handle multi-chain fund administration?</h3>\n<p></p>\n<p>Yes. Over 90% of the platform's features cover all chains and all wallets, and on-chain modules run on Ethereum, BNB Chain, and MultiversX today, with Polygon, Arbitrum, Avalanche, Optimism, and Solana coming.</p>\n<h3>How do participants track their vesting?</h3>\n<p></p>\n<p>Allocations update at least hourly, tokens arrive in participants' wallets at each vesting unlock event, and the platform sends reminders when unlocks are due.</p>\n<p>Non-custodial fund administration keeps control where it belongs, with the group. To see how it fits your syndicate, visit <a href=\"https://cryptool.io\" target=\"_blank\" rel=\"noopener\">cryptool.io</a>.</p>",
  "type": "blog",
  "author": "Cryptool",
  "excerpt_html": "Community VCs and crypto syndicates share a common problem. They want to pool capital, track member allocations, and run distributions without handing their ass",
  "tags": [
    "Fund Management"
  ],
  "cover": "https://amt.cryptool.io/media/kit-group-member-management-screenshot-1780145830429.png",
  "hero_image": "https://amt.cryptool.io/media/kit-group-member-management-screenshot-1780145830429.png"
}